LICENSE
README.md
pyproject.toml
setup.cfg
setup.py
competitors/__init__.py
competitors/latentmotifs.py
competitors/latentmotifs_numba.py
motiflets/__init__.py
motiflets/competitors.py
motiflets/distances.py
motiflets/knn_scampi_backend.py
motiflets/knn_vector_backend.py
motiflets/motiflets.py
motiflets/plotting.py
scampi.egg-info/PKG-INFO
scampi.egg-info/SOURCES.txt
scampi.egg-info/dependency_links.txt
scampi.egg-info/not-zip-safe
scampi.egg-info/requires.txt
scampi.egg-info/top_level.txt
tests/test_scalability.py
tests/test_sparse.py
tests/test_stitching.py